dom_retry_library.py
robot_ai_domretrylibrary/DomRetryLibrary.py
robot_ai_domretrylibrary/__init__.py
robot_ai_domretrylibrary/dom_retry_library.py
robot_ai_domretrylibrary/locator_comparison.json
robot_ai_domretrylibrary-0.1.3.dist-info/LICENSE
robot_ai_domretrylibrary-0.1.3.dist-info/METADATA
robot_ai_domretrylibrary-0.1.3.dist-info/WHEEL
robot_ai_domretrylibrary-0.1.3.dist-info/entry_points.txt
robot_ai_domretrylibrary-0.1.3.dist-info/top_level.txt
robot_ai_domretrylibrary-0.1.3.dist-info/RECORD
