Metadata-Version: 2.1
Name: robot-ai-domretrylibrary
Version: 0.1.3
Summary: A Robot Framework library with AI fallback for locators using OpenAI
Home-page: https://github.com/plaushku/robot-ai-domretrylibrary
Author: Kristijan Plaushku
Author-email: info@plaushkusolutions.com
License: UNKNOWN
Keywords: robotframework testing automation ai openai
Platform: UNKNOWN
Classifier: Programming Language :: Python :: 3
Classifier: Programming Language :: Python :: 3.8
Classifier: Programming Language :: Python :: 3.9
Classifier: Programming Language :: Python :: 3.10
Classifier: Framework :: Robot Framework :: Library
Classifier: License :: OSI Approved :: MIT License
Classifier: Operating System :: OS Independent
Classifier: Topic :: Software Development :: Testing
Classifier: Topic :: Software Development :: Testing :: Acceptance
Requires-Python: >=3.8
License-File: LICENSE
Requires-Dist: robotframework (>=6.0)
Requires-Dist: robotframework-seleniumlibrary (>=6.0)
Requires-Dist: python-dotenv (>=1.0.0)
Requires-Dist: requests (>=2.28.0)
Requires-Dist: webdriver-manager (>=4.0.0)
